plttools/__init__.py
plttools/ep_curve.py
plttools/plt.py
plttools/plt_calculator.py
plttools-0.1.1.dist-info/LICENSE
plttools-0.1.1.dist-info/METADATA
plttools-0.1.1.dist-info/WHEEL
plttools-0.1.1.dist-info/top_level.txt
plttools-0.1.1.dist-info/RECORD
