Metadata-Version: 2.1
Name: plttools
Version: 0.1.1
Summary: Interact with PLTs
Home-page: https://github.com/anishpatelwork/plttools
Author: Anish Patel
License: MIT
Platform: UNKNOWN
Requires-Dist: pandas
